damoov_admin/__init__.py
damoov_admin/accounts.py
damoov_admin/auth.py
damoov_admin/core.py
damoov_admin/engagement.py
damoov_admin/statistics.py
damoov_admin/trips.py
damoov_admin/users.py
damoov_admin/utility.py
damoov_admin/.resources/resources.sql
damoov_admin-0.9.7.dist-info/LICENSE
damoov_admin-0.9.7.dist-info/METADATA
damoov_admin-0.9.7.dist-info/WHEEL
damoov_admin-0.9.7.dist-info/top_level.txt
damoov_admin-0.9.7.dist-info/RECORD
