Metadata-Version: 2.2
Name: damoov_admin
Version: 0.9.7
Summary: SDK for Damoov's APIs
Author: Damoov
Author-email: admin@damoov.com
Keywords: damoov sdk telematics mobiletelematics safety driving safe-driving fleetmanagement fleet-management fleet driving-behavior driving-behaviour driving-behavior-analysis driving-behaviour-analysis driving-behavior-monitoring driving-behaviour-monitoring driving-behavior-score driving-behaviour-score driving-behavior-scoring driving-behaviour-scoring driving-behavior-analysis driving-behaviour-analysis driving-behavior-monitoring driving-behaviour-monitoring driving-behavior-score driving-
License-File: LICENSE
Requires-Dist: requests
Dynamic: author
Dynamic: author-email
Dynamic: description
Dynamic: description-content-type
Dynamic: keywords
Dynamic: requires-dist
Dynamic: summary
